LICENSE.txt
README.md
setup.py
SAMBA_ilum.egg-info/PKG-INFO
SAMBA_ilum.egg-info/SOURCES.txt
SAMBA_ilum.egg-info/dependency_links.txt
SAMBA_ilum.egg-info/entry_points.txt
SAMBA_ilum.egg-info/requires.txt
SAMBA_ilum.egg-info/top_level.txt
samba_ilum/__init__.py
samba_ilum/__main__.py
samba_ilum/src/BZ_2D.py
samba_ilum/src/BibTeX.dat
samba_ilum/src/HeteroStructure_Generator.py
samba_ilum/src/_info_pseudo.py
samba_ilum/src/_vasprocar.py
samba_ilum/src/a-scan.py
samba_ilum/src/a-scan_analysis.py
samba_ilum/src/bader
samba_ilum/src/bader_poscar.py
samba_ilum/src/bader_update.py
samba_ilum/src/cell_check.py
samba_ilum/src/charge_transfer.py
samba_ilum/src/chgsum.pl
samba_ilum/src/contcar_update.py
samba_ilum/src/data-base_json.py
samba_ilum/src/data-base_union.py
samba_ilum/src/energy_scan.py
samba_ilum/src/hubbard_correction.py
samba_ilum/src/job.py
samba_ilum/src/kpoints.py
samba_ilum/src/lattice_plot3d.py
samba_ilum/src/make_files.py
samba_ilum/src/miller_confine.py
samba_ilum/src/output.py
samba_ilum/src/poscar_fix_direct_coord.py
samba_ilum/src/potcar.py
samba_ilum/src/vdW_DF.py
samba_ilum/src/xy-scan.py
samba_ilum/src/xy-scan_analysis.py
samba_ilum/src/xyz-scan.py
samba_ilum/src/xyz-scan_analysis.py
samba_ilum/src/z-scan.py
samba_ilum/src/z-scan_analysis.py
samba_ilum/src/INPUTS/Hubbard_U_values.txt
samba_ilum/src/INPUTS/INCAR_a-scan
samba_ilum/src/INPUTS/INCAR_bader
samba_ilum/src/INPUTS/INCAR_bader.SO
samba_ilum/src/INPUTS/INCAR_bands
samba_ilum/src/INPUTS/INCAR_bands.SO
samba_ilum/src/INPUTS/INCAR_dos
samba_ilum/src/INPUTS/INCAR_dos.SO
samba_ilum/src/INPUTS/INCAR_relax
samba_ilum/src/INPUTS/INCAR_scf
samba_ilum/src/INPUTS/INCAR_scf.SO
samba_ilum/src/INPUTS/INCAR_xy-scan
samba_ilum/src/INPUTS/INCAR_xyz-scan
samba_ilum/src/INPUTS/INCAR_z-scan
samba_ilum/src/INPUTS/SAMBA_HeteroStructure.input
samba_ilum/src/INPUTS/SAMBA_WorkFlow.input
samba_ilum/src/INPUTS/vdw_kernel.bindat
samba_ilum/src/INPUTS/inputs_VASProcar/input.vasprocar.bands
samba_ilum/src/INPUTS/inputs_VASProcar/input.vasprocar.chgcar
samba_ilum/src/INPUTS/inputs_VASProcar/input.vasprocar.dos
samba_ilum/src/INPUTS/inputs_VASProcar/input.vasprocar.location
