Metadata-Version: 2.1
Name: SAMBA_ilum
Version: 1.1.0.146
Summary: The SAMBA code is an open-source, high-throughput Python workflow for generating, simulating, and analyzing twisted bilayers. It features modules for: (i) creating thousands of quasi-commensurate structures via the coincidence lattice method; (ii) assist in the running DFT calculations using VASP; and (iii) extracting and organizing structural, electronic, and energetic properties into a robust dataset.
Author: Augusto de Lelis Araujo
Author-email: augusto-lelis@outlook.com
License: GNU General Public License v3.0
License-File: LICENSE.txt
Requires-Dist: matplotlib
Requires-Dist: pymatgen
Requires-Dist: pyfiglet
Requires-Dist: requests
Requires-Dist: plotly
Requires-Dist: scipy
Requires-Dist: numpy
Requires-Dist: uuid
Requires-Dist: ase
Requires-Dist: vasprocar
